[
    {
        "rank": 1,
        "name": "Azrion Zeuion",
        "inf_kills": 136,
        "soft_veh": 0,
        "armor_veh": 2,
        "air": 0,
        "deaths": 0,
        "score": 142
    },
    {
        "rank": 2,
        "name": "Neacal Dracion",
        "inf_kills": 46,
        "soft_veh": 0,
        "armor_veh": 21,
        "air": 1,
        "deaths": 0,
        "score": 114
    },
    {
        "rank": 3,
        "name": "Avar Ulbrecht",
        "inf_kills": 58,
        "soft_veh": 0,
        "armor_veh": 7,
        "air": 0,
        "deaths": 0,
        "score": 79
    },
    {
        "rank": 4,
        "name": "Esurien Mortuus",
        "inf_kills": 68,
        "soft_veh": 0,
        "armor_veh": 1,
        "air": 1,
        "deaths": 0,
        "score": 76
    },
    {
        "rank": 5,
        "name": "Mosk Pius",
        "inf_kills": 58,
        "soft_veh": 0,
        "armor_veh": 4,
        "air": 0,
        "deaths": 3,
        "score": 70
    },
    {
        "rank": 6,
        "name": "Wolf Tribune",
        "inf_kills": 58,
        "soft_veh": 0,
        "armor_veh": 0,
        "air": 1,
        "deaths": 2,
        "score": 63
    },
    {
        "rank": 7,
        "name": "Seanicus Asterphon",
        "inf_kills": 60,
        "soft_veh": 0,
        "armor_veh": 0,
        "air": 0,
        "deaths": 4,
        "score": 60
    },
    {
        "rank": 8,
        "name": "Lysander Orosius",
        "inf_kills": 53,
        "soft_veh": 0,
        "armor_veh": 2,
        "air": 0,
        "deaths": 2,
        "score": 59
    },
    {
        "rank": 9,
        "name": "Sonos Calgist",
        "inf_kills": 43,
        "soft_veh": 0,
        "armor_veh": 0,
        "air": 0,
        "deaths": 4,
        "score": 43
    },
    {
        "rank": 10,
        "name": "Malrinius Manus",
        "inf_kills": 38,
        "soft_veh": 0,
        "armor_veh": 1,
        "air": 0,
        "deaths": 3,
        "score": 41
    },
    {
        "rank": 11,
        "name": "Castian Rozila",
        "inf_kills": 25,
        "soft_veh": 0,
        "armor_veh": 1,
        "air": 2,
        "deaths": 3,
        "score": 38
    },
    {
        "rank": 12,
        "name": "Helios Galadin",
        "inf_kills": 34,
        "soft_veh": 0,
        "armor_veh": 1,
        "air": 0,
        "deaths": 5,
        "score": 37
    },
    {
        "rank": 13,
        "name": "Azazel Magrio",
        "inf_kills": 30,
        "soft_veh": 0,
        "armor_veh": 1,
        "air": 0,
        "deaths": 6,
        "score": 33
    },
    {
        "rank": 14,
        "name": "Ven Erath",
        "inf_kills": 29,
        "soft_veh": 0,
        "armor_veh": 0,
        "air": 0,
        "deaths": 3,
        "score": 29
    },
    {
        "rank": 15,
        "name": "Kane Corvar",
        "inf_kills": 23,
        "soft_veh": 0,
        "armor_veh": 1,
        "air": 0,
        "deaths": 2,
        "score": 26
    },
    {
        "rank": 16,
        "name": "Omneil Noctus",
        "inf_kills": 25,
        "soft_veh": 0,
        "armor_veh": 0,
        "air": 0,
        "deaths": 4,
        "score": 25
    },
    {
        "rank": 17,
        "name": "Tyberos Scharn",
        "inf_kills": 23,
        "soft_veh": 0,
        "armor_veh": 0,
        "air": 0,
        "deaths": 0,
        "score": 23
    },
    {
        "rank": 18,
        "name": "Balderic Caeledis",
        "inf_kills": 18,
        "soft_veh": 0,
        "armor_veh": 0,
        "air": 0,
        "deaths": 1,
        "score": 18
    },
    {
        "rank": 19,
        "name": "Alarak Sicarius",
        "inf_kills": 7,
        "soft_veh": 0,
        "armor_veh": 2,
        "air": 1,
        "deaths": 7,
        "score": 18
    },
    {
        "rank": 20,
        "name": "Arrathus Decinian",
        "inf_kills": 16,
        "soft_veh": 0,
        "armor_veh": 0,
        "air": 0,
        "deaths": 5,
        "score": 16
    },
    {
        "rank": 21,
        "name": "Sergio Xandus",
        "inf_kills": 11,
        "soft_veh": 0,
        "armor_veh": 0,
        "air": 0,
        "deaths": 4,
        "score": 11
    },
    {
        "rank": 22,
        "name": "Horatio Loran",
        "inf_kills": 5,
        "soft_veh": 0,
        "armor_veh": 0,
        "air": 0,
        "deaths": 7,
        "score": 5
    },
    {
        "rank": 23,
        "name": "Venerable Wolfhart",
        "inf_kills": 1,
        "soft_veh": 0,
        "armor_veh": 0,
        "air": 0,
        "deaths": 0,
        "score": 1
    },
    {
        "rank": 24,
        "name": "Domayne Expanshun",
        "inf_kills": -2,
        "soft_veh": 0,
        "armor_veh": -1,
        "air": 1,
        "deaths": 0,
        "score": 0
    },
    {
        "rank": 25,
        "name": "Gallus Stanz",
        "inf_kills": 0,
        "soft_veh": 0,
        "armor_veh": 0,
        "air": 0,
        "deaths": 3,
        "score": 0
    },
    {
        "rank": 26,
        "name": "Sedric Richter",
        "inf_kills": -1,
        "soft_veh": 0,
        "armor_veh": -1,
        "air": 0,
        "deaths": 0,
        "score": -4
    }
]