[
    {
        "rank": 1,
        "name": "Azrion Zeuion",
        "inf_kills": 137,
        "soft_veh": 0,
        "armor_veh": 0,
        "air": 0,
        "deaths": 0,
        "score": 137
    },
    {
        "rank": 2,
        "name": "Seanicus Asterphon",
        "inf_kills": 83,
        "soft_veh": 0,
        "armor_veh": 7,
        "air": 0,
        "deaths": 1,
        "score": 104
    },
    {
        "rank": 3,
        "name": "Lucius Sellion",
        "inf_kills": 85,
        "soft_veh": 0,
        "armor_veh": 3,
        "air": 0,
        "deaths": 1,
        "score": 94
    },
    {
        "rank": 4,
        "name": "Tarkor Tirax",
        "inf_kills": 78,
        "soft_veh": 0,
        "armor_veh": 0,
        "air": 0,
        "deaths": 0,
        "score": 78
    },
    {
        "rank": 5,
        "name": "Alarak Sicarius",
        "inf_kills": 62,
        "soft_veh": 0,
        "armor_veh": 0,
        "air": 0,
        "deaths": 1,
        "score": 62
    },
    {
        "rank": 6,
        "name": "Gavriel Linderman",
        "inf_kills": 52,
        "soft_veh": 0,
        "armor_veh": 2,
        "air": 0,
        "deaths": 1,
        "score": 58
    },
    {
        "rank": 7,
        "name": "Tyberos Scharn",
        "inf_kills": 48,
        "soft_veh": 0,
        "armor_veh": 0,
        "air": 0,
        "deaths": 1,
        "score": 48
    },
    {
        "rank": 8,
        "name": "Omesias Fasandar",
        "inf_kills": 48,
        "soft_veh": 0,
        "armor_veh": 0,
        "air": 0,
        "deaths": 4,
        "score": 48
    },
    {
        "rank": 9,
        "name": "Barabas Barbarossa",
        "inf_kills": 39,
        "soft_veh": 0,
        "armor_veh": 1,
        "air": 0,
        "deaths": 2,
        "score": 42
    },
    {
        "rank": 10,
        "name": "Alastair Darksmith",
        "inf_kills": 34,
        "soft_veh": 0,
        "armor_veh": 4,
        "air": -1,
        "deaths": 0,
        "score": 41
    },
    {
        "rank": 11,
        "name": "Bastallan Provectus",
        "inf_kills": 31,
        "soft_veh": 0,
        "armor_veh": 3,
        "air": 0,
        "deaths": 3,
        "score": 40
    },
    {
        "rank": 12,
        "name": "Asmodai Achumfeld",
        "inf_kills": 24,
        "soft_veh": 0,
        "armor_veh": 5,
        "air": 0,
        "deaths": 0,
        "score": 39
    },
    {
        "rank": 13,
        "name": "Castus Caedus",
        "inf_kills": 36,
        "soft_veh": 0,
        "armor_veh": 0,
        "air": 0,
        "deaths": 1,
        "score": 36
    },
    {
        "rank": 14,
        "name": "Xarl Endymion",
        "inf_kills": 34,
        "soft_veh": 0,
        "armor_veh": 0,
        "air": 0,
        "deaths": 2,
        "score": 34
    },
    {
        "rank": 15,
        "name": "Kitus Numquar",
        "inf_kills": 34,
        "soft_veh": 0,
        "armor_veh": 0,
        "air": 0,
        "deaths": 2,
        "score": 34
    },
    {
        "rank": 16,
        "name": "Miron Sigiseton",
        "inf_kills": 34,
        "soft_veh": 0,
        "armor_veh": 0,
        "air": 0,
        "deaths": 2,
        "score": 34
    },
    {
        "rank": 17,
        "name": "Sergio Xandus",
        "inf_kills": 32,
        "soft_veh": 0,
        "armor_veh": 0,
        "air": 0,
        "deaths": 1,
        "score": 32
    },
    {
        "rank": 18,
        "name": "Asterion Theross",
        "inf_kills": 31,
        "soft_veh": 0,
        "armor_veh": 0,
        "air": 0,
        "deaths": 1,
        "score": 31
    },
    {
        "rank": 19,
        "name": "Esurien Mortuus",
        "inf_kills": 29,
        "soft_veh": 0,
        "armor_veh": 0,
        "air": 0,
        "deaths": 1,
        "score": 29
    },
    {
        "rank": 20,
        "name": "Cyro Tius",
        "inf_kills": 27,
        "soft_veh": 0,
        "armor_veh": 0,
        "air": 0,
        "deaths": 0,
        "score": 27
    },
    {
        "rank": 21,
        "name": "Arnulf Innum",
        "inf_kills": 21,
        "soft_veh": 0,
        "armor_veh": 1,
        "air": 0,
        "deaths": 3,
        "score": 24
    },
    {
        "rank": 22,
        "name": "Diego Tykus",
        "inf_kills": 23,
        "soft_veh": 0,
        "armor_veh": 0,
        "air": 0,
        "deaths": 0,
        "score": 23
    },
    {
        "rank": 23,
        "name": "Nagetier Chronik",
        "inf_kills": 21,
        "soft_veh": 0,
        "armor_veh": 0,
        "air": 0,
        "deaths": 3,
        "score": 21
    },
    {
        "rank": 24,
        "name": "Drekarius Tharren",
        "inf_kills": 20,
        "soft_veh": 0,
        "armor_veh": 0,
        "air": 0,
        "deaths": 0,
        "score": 20
    },
    {
        "rank": 25,
        "name": "Tyrian Halbalas",
        "inf_kills": 19,
        "soft_veh": 0,
        "armor_veh": 0,
        "air": 0,
        "deaths": 0,
        "score": 19
    },
    {
        "rank": 26,
        "name": "Byconis Volitans",
        "inf_kills": 19,
        "soft_veh": 0,
        "armor_veh": 0,
        "air": 0,
        "deaths": 2,
        "score": 19
    },
    {
        "rank": 27,
        "name": "Fernus Gerauden",
        "inf_kills": 17,
        "soft_veh": 0,
        "armor_veh": 0,
        "air": 0,
        "deaths": 2,
        "score": 17
    },
    {
        "rank": 28,
        "name": "Georgio Tiberius",
        "inf_kills": 10,
        "soft_veh": 0,
        "armor_veh": 1,
        "air": 0,
        "deaths": 0,
        "score": 13
    },
    {
        "rank": 29,
        "name": "Luceus Caphriel",
        "inf_kills": 10,
        "soft_veh": 0,
        "armor_veh": 0,
        "air": 0,
        "deaths": 1,
        "score": 10
    },
    {
        "rank": 30,
        "name": "Artyios Lysem",
        "inf_kills": 9,
        "soft_veh": 0,
        "armor_veh": 0,
        "air": 0,
        "deaths": 0,
        "score": 9
    },
    {
        "rank": 31,
        "name": "Ven Erath",
        "inf_kills": 8,
        "soft_veh": 0,
        "armor_veh": 0,
        "air": 0,
        "deaths": 0,
        "score": 8
    },
    {
        "rank": 32,
        "name": "Severam Black",
        "inf_kills": 6,
        "soft_veh": 0,
        "armor_veh": 0,
        "air": 0,
        "deaths": 2,
        "score": 6
    },
    {
        "rank": 33,
        "name": "Sedric Richter",
        "inf_kills": 3,
        "soft_veh": 0,
        "armor_veh": 0,
        "air": 0,
        "deaths": 2,
        "score": 6
    },
    {
        "rank": 34,
        "name": "Klause Werner",
        "inf_kills": 4,
        "soft_veh": 0,
        "armor_veh": 0,
        "air": 0,
        "deaths": 2,
        "score": 4
    },
    {
        "rank": 35,
        "name": "Cyrus King",
        "inf_kills": 3,
        "soft_veh": 0,
        "armor_veh": 0,
        "air": 0,
        "deaths": 0,
        "score": 3
    },
    {
        "rank": 36,
        "name": "Baelot Issyras",
        "inf_kills": 1,
        "soft_veh": 0,
        "armor_veh": 0,
        "air": 0,
        "deaths": 0,
        "score": 1
    },
    {
        "rank": 37,
        "name": "Alistar Tebes",
        "inf_kills": 0,
        "soft_veh": 0,
        "armor_veh": 0,
        "air": 0,
        "deaths": 0,
        "score": 0
    },
    {
        "rank": 38,
        "name": "Titus Marinius",
        "inf_kills": 0,
        "soft_veh": 0,
        "armor_veh": 0,
        "air": 0,
        "deaths": 0,
        "score": 0
    },
    {
        "rank": 40,
        "name": "Turelius Triarii",
        "inf_kills": 0,
        "soft_veh": 0,
        "armor_veh": 0,
        "air": 0,
        "deaths": 2,
        "score": 0
    },
    {
        "rank": 41,
        "name": "Venerable Wolfhart",
        "inf_kills": 0,
        "soft_veh": 0,
        "armor_veh": 0,
        "air": 0,
        "deaths": 0,
        "score": 0
    },
    {
        "rank": 42,
        "name": "Tridexus Tychmund",
        "inf_kills": 0,
        "soft_veh": 0,
        "armor_veh": 0,
        "air": 0,
        "deaths": 5,
        "score": 0
    }
]