[
    {
        "rank": 1,
        "name": "Dagonel Griffor",
        "inf_kills": 153,
        "soft_veh": 1,
        "armor_veh": 2,
        "air": 1,
        "deaths": 0,
        "score": 166
    },
    {
        "rank": 2,
        "name": "Azrion Zeuion",
        "inf_kills": 115,
        "soft_veh": 3,
        "armor_veh": 0,
        "air": -1,
        "deaths": 0,
        "score": 116
    },
    {
        "rank": 3,
        "name": "Wolf Tribune",
        "inf_kills": 60,
        "soft_veh": -2,
        "armor_veh": 7,
        "air": 1,
        "deaths": 2,
        "score": 82
    },
    {
        "rank": 4,
        "name": "Ash Farhammer",
        "inf_kills": 24,
        "soft_veh": 0,
        "armor_veh": 10,
        "air": 2,
        "deaths": 0,
        "score": 64
    },
    {
        "rank": 5,
        "name": "Adrius Auxilius",
        "inf_kills": 62,
        "soft_veh": 0,
        "armor_veh": 0,
        "air": 0,
        "deaths": 0,
        "score": 62
    },
    {
        "rank": 6,
        "name": "Fernus Gerauden",
        "inf_kills": 61,
        "soft_veh": 0,
        "armor_veh": 0,
        "air": 0,
        "deaths": 1,
        "score": 61
    },
    {
        "rank": 7,
        "name": "Heinrich Skoll",
        "inf_kills": 54,
        "soft_veh": 0,
        "armor_veh": 0,
        "air": 0,
        "deaths": 0,
        "score": 54
    },
    {
        "rank": 8,
        "name": "Vel'tek Aquila",
        "inf_kills": 32,
        "soft_veh": -1,
        "armor_veh": 7,
        "air": 0,
        "deaths": 0,
        "score": 51
    },
    {
        "rank": 9,
        "name": "Esurien Mortuus",
        "inf_kills": 48,
        "soft_veh": 0,
        "armor_veh": 0,
        "air": 0,
        "deaths": 0,
        "score": 48
    },
    {
        "rank": 10,
        "name": "Lysander Orosius",
        "inf_kills": 47,
        "soft_veh": 0,
        "armor_veh": 0,
        "air": 0,
        "deaths": 1,
        "score": 47
    },
    {
        "rank": 11,
        "name": "Proximos Arios",
        "inf_kills": 39,
        "soft_veh": 0,
        "armor_veh": 2,
        "air": 0,
        "deaths": 0,
        "score": 45
    },
    {
        "rank": 12,
        "name": "Miron Sigiseton",
        "inf_kills": 45,
        "soft_veh": 0,
        "armor_veh": 0,
        "air": 0,
        "deaths": 1,
        "score": 45
    },
    {
        "rank": 13,
        "name": "Horatio Loran",
        "inf_kills": 39,
        "soft_veh": 0,
        "armor_veh": 1,
        "air": 0,
        "deaths": 1,
        "score": 42
    },
    {
        "rank": 14,
        "name": "Ezekiel Rayner",
        "inf_kills": 37,
        "soft_veh": 0,
        "armor_veh": 0,
        "air": 0,
        "deaths": 0,
        "score": 37
    },
    {
        "rank": 15,
        "name": "Arrathus Decinian",
        "inf_kills": 35,
        "soft_veh": 0,
        "armor_veh": 0,
        "air": 0,
        "deaths": 1,
        "score": 35
    },
    {
        "rank": 16,
        "name": "Alajos Ortykus",
        "inf_kills": 34,
        "soft_veh": 0,
        "armor_veh": 0,
        "air": 0,
        "deaths": 0,
        "score": 34
    },
    {
        "rank": 17,
        "name": "Zaros Kestandus",
        "inf_kills": 32,
        "soft_veh": 0,
        "armor_veh": 0,
        "air": 0,
        "deaths": 0,
        "score": 32
    },
    {
        "rank": 18,
        "name": "Seanicus Asterphon",
        "inf_kills": 28,
        "soft_veh": 2,
        "armor_veh": 0,
        "air": 0,
        "deaths": 3,
        "score": 32
    },
    {
        "rank": 19,
        "name": "Gerhard Ortelius",
        "inf_kills": 30,
        "soft_veh": 0,
        "armor_veh": 0,
        "air": 0,
        "deaths": 0,
        "score": 30
    },
    {
        "rank": 20,
        "name": "Sedric Richter",
        "inf_kills": 12,
        "soft_veh": 0,
        "armor_veh": 7,
        "air": -1,
        "deaths": 1,
        "score": 28
    },
    {
        "rank": 21,
        "name": "Seqtur Clades",
        "inf_kills": 24,
        "soft_veh": 0,
        "armor_veh": 0,
        "air": 0,
        "deaths": 0,
        "score": 24
    },
    {
        "rank": 22,
        "name": "Cyrus King",
        "inf_kills": 21,
        "soft_veh": 0,
        "armor_veh": 0,
        "air": 0,
        "deaths": 0,
        "score": 21
    },
    {
        "rank": 23,
        "name": "Julius Brazenheart",
        "inf_kills": 19,
        "soft_veh": 0,
        "armor_veh": 0,
        "air": 0,
        "deaths": 0,
        "score": 19
    },
    {
        "rank": 24,
        "name": "Vorac Forimus",
        "inf_kills": 18,
        "soft_veh": 0,
        "armor_veh": 0,
        "air": 0,
        "deaths": 0,
        "score": 18
    },
    {
        "rank": 25,
        "name": "Xarl Endymion",
        "inf_kills": 18,
        "soft_veh": 0,
        "armor_veh": 0,
        "air": 0,
        "deaths": 3,
        "score": 18
    },
    {
        "rank": 26,
        "name": "Delt Timez",
        "inf_kills": 6,
        "soft_veh": 0,
        "armor_veh": 1,
        "air": 0,
        "deaths": 0,
        "score": 9
    },
    {
        "rank": 27,
        "name": "Yutari Voloricus",
        "inf_kills": 0,
        "soft_veh": 0,
        "armor_veh": 0,
        "air": 0,
        "deaths": 0,
        "score": 0
    },
    {
        "rank": 28,
        "name": "Arephicus Cordatanus",
        "inf_kills": 0,
        "soft_veh": 0,
        "armor_veh": 0,
        "air": 0,
        "deaths": 1,
        "score": 0
    },
    {
        "rank": 29,
        "name": "Cyro Tius",
        "inf_kills": 0,
        "soft_veh": 0,
        "armor_veh": 0,
        "air": 0,
        "deaths": 2,
        "score": 0
    },
    {
        "rank": 30,
        "name": "Castian Rozila",
        "inf_kills": -1,
        "soft_veh": 0,
        "armor_veh": 0,
        "air": 0,
        "deaths": 1,
        "score": -1
    }
]