[
    {
        "rank": 1,
        "name": "Fin Enarah",
        "inf_kills": 98,
        "soft_veh": 0,
        "armor_veh": 38,
        "air": 15,
        "deaths": 0,
        "score": 287
    },
    {
        "rank": 2,
        "name": "Seanicus Asterphon",
        "inf_kills": 255,
        "soft_veh": 0,
        "armor_veh": 3,
        "air": 0,
        "deaths": 2,
        "score": 264
    },
    {
        "rank": 3,
        "name": "Moss Caessian",
        "inf_kills": 227,
        "soft_veh": 0,
        "armor_veh": 9,
        "air": 1,
        "deaths": 5,
        "score": 259
    },
    {
        "rank": 4,
        "name": "Xetor Alanclaest",
        "inf_kills": 241,
        "soft_veh": 0,
        "armor_veh": 0,
        "air": 0,
        "deaths": 3,
        "score": 241
    },
    {
        "rank": 5,
        "name": "Kane Corvar",
        "inf_kills": 219,
        "soft_veh": 0,
        "armor_veh": 0,
        "air": 0,
        "deaths": 0,
        "score": 219
    },
    {
        "rank": 6,
        "name": "Orthicus Otto",
        "inf_kills": 197,
        "soft_veh": 0,
        "armor_veh": 0,
        "air": 0,
        "deaths": 0,
        "score": 197
    },
    {
        "rank": 7,
        "name": "Wolfstille Krause",
        "inf_kills": 181,
        "soft_veh": 0,
        "armor_veh": 1,
        "air": 0,
        "deaths": 0,
        "score": 184
    },
    {
        "rank": 8,
        "name": "Dogarius Kaledon",
        "inf_kills": 135,
        "soft_veh": 0,
        "armor_veh": 5,
        "air": 0,
        "deaths": 1,
        "score": 150
    },
    {
        "rank": 9,
        "name": "Herius Occisor",
        "inf_kills": 145,
        "soft_veh": 0,
        "armor_veh": 1,
        "air": 0,
        "deaths": 1,
        "score": 148
    },
    {
        "rank": 10,
        "name": "Dagonel Griffor",
        "inf_kills": 124,
        "soft_veh": 0,
        "armor_veh": 4,
        "air": 0,
        "deaths": 3,
        "score": 136
    },
    {
        "rank": 11,
        "name": "Dantanius Lunius",
        "inf_kills": 131,
        "soft_veh": 0,
        "armor_veh": 0,
        "air": 0,
        "deaths": 4,
        "score": 131
    },
    {
        "rank": 12,
        "name": "Toroc Arakia",
        "inf_kills": 124,
        "soft_veh": 0,
        "armor_veh": 0,
        "air": 0,
        "deaths": 2,
        "score": 124
    },
    {
        "rank": 13,
        "name": "Azrion Zeuion",
        "inf_kills": 113,
        "soft_veh": 0,
        "armor_veh": 0,
        "air": 0,
        "deaths": 1,
        "score": 113
    },
    {
        "rank": 14,
        "name": "Nerovar Wolff",
        "inf_kills": 102,
        "soft_veh": 0,
        "armor_veh": 3,
        "air": 0,
        "deaths": 2,
        "score": 111
    },
    {
        "rank": 15,
        "name": "Zacharia Wolff",
        "inf_kills": 106,
        "soft_veh": 0,
        "armor_veh": 0,
        "air": 0,
        "deaths": 1,
        "score": 106
    },
    {
        "rank": 16,
        "name": "Raykan Hussarion",
        "inf_kills": 103,
        "soft_veh": 0,
        "armor_veh": 0,
        "air": 0,
        "deaths": 0,
        "score": 103
    },
    {
        "rank": 17,
        "name": "Micaius Valerrion",
        "inf_kills": 101,
        "soft_veh": 0,
        "armor_veh": 0,
        "air": 0,
        "deaths": 2,
        "score": 101
    },
    {
        "rank": 18,
        "name": "Lysander Orosius",
        "inf_kills": 90,
        "soft_veh": 0,
        "armor_veh": 3,
        "air": 0,
        "deaths": 0,
        "score": 99
    },
    {
        "rank": 19,
        "name": "Wilhelm King",
        "inf_kills": 88,
        "soft_veh": 0,
        "armor_veh": 1,
        "air": 0,
        "deaths": 1,
        "score": 91
    },
    {
        "rank": 20,
        "name": "Usiel Dranacht",
        "inf_kills": 83,
        "soft_veh": 0,
        "armor_veh": 0,
        "air": 0,
        "deaths": 2,
        "score": 83
    },
    {
        "rank": 21,
        "name": "Zeliom Cavon",
        "inf_kills": 83,
        "soft_veh": 0,
        "armor_veh": 0,
        "air": 0,
        "deaths": 2,
        "score": 83
    },
    {
        "rank": 22,
        "name": "Vespera Aetos",
        "inf_kills": 71,
        "soft_veh": 0,
        "armor_veh": 0,
        "air": 0,
        "deaths": 0,
        "score": 71
    },
    {
        "rank": 23,
        "name": "Seraph Historia",
        "inf_kills": 71,
        "soft_veh": 0,
        "armor_veh": 0,
        "air": 0,
        "deaths": 1,
        "score": 71
    },
    {
        "rank": 24,
        "name": "Zeruel Monarch",
        "inf_kills": 53,
        "soft_veh": 0,
        "armor_veh": 1,
        "air": 0,
        "deaths": 0,
        "score": 56
    },
    {
        "rank": 25,
        "name": "Siniel Arakia",
        "inf_kills": 43,
        "soft_veh": 0,
        "armor_veh": 0,
        "air": 0,
        "deaths": 0,
        "score": 43
    },
    {
        "rank": 26,
        "name": "Fiorstan Sharris",
        "inf_kills": 41,
        "soft_veh": 0,
        "armor_veh": 0,
        "air": 0,
        "deaths": 0,
        "score": 41
    },
    {
        "rank": 27,
        "name": "Sergio Xandus",
        "inf_kills": 39,
        "soft_veh": 0,
        "armor_veh": 0,
        "air": 0,
        "deaths": 1,
        "score": 39
    },
    {
        "rank": 28,
        "name": "Harvos Liche",
        "inf_kills": 27,
        "soft_veh": 0,
        "armor_veh": 2,
        "air": 0,
        "deaths": 1,
        "score": 33
    },
    {
        "rank": 29,
        "name": "Omneil Noctus",
        "inf_kills": 21,
        "soft_veh": 0,
        "armor_veh": 0,
        "air": 0,
        "deaths": 1,
        "score": 21
    },
    {
        "rank": 30,
        "name": "Frederus Arbrecht",
        "inf_kills": 15,
        "soft_veh": 0,
        "armor_veh": 1,
        "air": 0,
        "deaths": 0,
        "score": 18
    },
    {
        "rank": 31,
        "name": "Wolf Tribune",
        "inf_kills": 4,
        "soft_veh": 0,
        "armor_veh": 0,
        "air": 0,
        "deaths": 0,
        "score": 4
    },
    {
        "rank": 32,
        "name": "Alastor Moratorn",
        "inf_kills": 2,
        "soft_veh": 0,
        "armor_veh": 0,
        "air": 0,
        "deaths": 0,
        "score": 2
    },
    {
        "rank": 33,
        "name": "Shephard Reynauld",
        "inf_kills": 1,
        "soft_veh": 0,
        "armor_veh": 0,
        "air": 0,
        "deaths": 0,
        "score": 1
    },
    {
        "rank": 34,
        "name": "Radiolus Asherail",
        "inf_kills": 0,
        "soft_veh": 0,
        "armor_veh": 0,
        "air": 0,
        "deaths": 1,
        "score": 0
    }
]