[
    {
        "rank": 1,
        "name": "Azrion Zeuion",
        "inf_kills": 420,
        "soft_veh": 2,
        "armor_veh": 3,
        "air": 0,
        "deaths": 0,
        "score": 433
    },
    {
        "rank": 2,
        "name": "Seanicus Asterphon",
        "inf_kills": 215,
        "soft_veh": 7,
        "armor_veh": 17,
        "air": 10,
        "deaths": 0,
        "score": 330
    },
    {
        "rank": 3,
        "name": "Moss Caessian",
        "inf_kills": 171,
        "soft_veh": 0,
        "armor_veh": 16,
        "air": 1,
        "deaths": 0,
        "score": 224
    },
    {
        "rank": 4,
        "name": "Xarl Endymion",
        "inf_kills": 162,
        "soft_veh": 0,
        "armor_veh": 7,
        "air": 0,
        "deaths": 0,
        "score": 183
    },
    {
        "rank": 5,
        "name": "Praeto Morellius",
        "inf_kills": 122,
        "soft_veh": 0,
        "armor_veh": 2,
        "air": 0,
        "deaths": 0,
        "score": 128
    },
    {
        "rank": 6,
        "name": "Kyr'ad Voss",
        "inf_kills": 62,
        "soft_veh": 1,
        "armor_veh": 0,
        "air": 9,
        "deaths": 2,
        "score": 109
    },
    {
        "rank": 7,
        "name": "Gregor Tiberius",
        "inf_kills": 104,
        "soft_veh": 0,
        "armor_veh": 0,
        "air": 0,
        "deaths": 0,
        "score": 104
    },
    {
        "rank": 8,
        "name": "Kase Caseus",
        "inf_kills": 74,
        "soft_veh": 0,
        "armor_veh": 7,
        "air": 1,
        "deaths": 0,
        "score": 100
    },
    {
        "rank": 9,
        "name": "Soladorr Cleardane",
        "inf_kills": 71,
        "soft_veh": 0,
        "armor_veh": 4,
        "air": 0,
        "deaths": 0,
        "score": 83
    },
    {
        "rank": 10,
        "name": "Asmodai Achumfeld",
        "inf_kills": 74,
        "soft_veh": 0,
        "armor_veh": 0,
        "air": 0,
        "deaths": 0,
        "score": 74
    },
    {
        "rank": 11,
        "name": "Soren Lysas",
        "inf_kills": 67,
        "soft_veh": 2,
        "armor_veh": 0,
        "air": 0,
        "deaths": 1,
        "score": 74
    },
    {
        "rank": 12,
        "name": "Jezor Tychian",
        "inf_kills": 68,
        "soft_veh": 0,
        "armor_veh": 2,
        "air": 0,
        "deaths": 2,
        "score": 74
    },
    {
        "rank": 13,
        "name": "Esurien Mortuus",
        "inf_kills": 50,
        "soft_veh": 0,
        "armor_veh": 1,
        "air": 0,
        "deaths": 0,
        "score": 73
    },
    {
        "rank": 14,
        "name": "Apharic Decion",
        "inf_kills": 71,
        "soft_veh": 0,
        "armor_veh": 0,
        "air": 0,
        "deaths": 0,
        "score": 71
    },
    {
        "rank": 15,
        "name": "Alastor Moratorn",
        "inf_kills": 38,
        "soft_veh": 0,
        "armor_veh": 2,
        "air": 5,
        "deaths": 3,
        "score": 69
    },
    {
        "rank": 16,
        "name": "Toroc Arakia",
        "inf_kills": 67,
        "soft_veh": 0,
        "armor_veh": 0,
        "air": 0,
        "deaths": 0,
        "score": 67
    },
    {
        "rank": 17,
        "name": "Arakas Iydroth",
        "inf_kills": 63,
        "soft_veh": 0,
        "armor_veh": 1,
        "air": 0,
        "deaths": 0,
        "score": 66
    },
    {
        "rank": 18,
        "name": "Arrathus Decinian",
        "inf_kills": 54,
        "soft_veh": 0,
        "armor_veh": 4,
        "air": 0,
        "deaths": 0,
        "score": 66
    },
    {
        "rank": 20,
        "name": "Lysander Orosius",
        "inf_kills": 53,
        "soft_veh": 0,
        "armor_veh": 0,
        "air": 0,
        "deaths": 1,
        "score": 53
    },
    {
        "rank": 21,
        "name": "Castian Rozila",
        "inf_kills": 37,
        "soft_veh": 2,
        "armor_veh": 2,
        "air": 1,
        "deaths": 0,
        "score": 52
    },
    {
        "rank": 22,
        "name": "Radiolus Asherail",
        "inf_kills": 44,
        "soft_veh": 0,
        "armor_veh": 2,
        "air": 0,
        "deaths": 0,
        "score": 50
    },
    {
        "rank": 23,
        "name": "Avar Torismund",
        "inf_kills": 32,
        "soft_veh": 0,
        "armor_veh": 0,
        "air": 0,
        "deaths": 0,
        "score": 32
    },
    {
        "rank": 24,
        "name": "Sebastian Emrik",
        "inf_kills": 26,
        "soft_veh": 0,
        "armor_veh": 1,
        "air": 0,
        "deaths": 1,
        "score": 29
    },
    {
        "rank": 25,
        "name": "Chinn Agustius",
        "inf_kills": 28,
        "soft_veh": 0,
        "armor_veh": 0,
        "air": 0,
        "deaths": 0,
        "score": 28
    },
    {
        "rank": 26,
        "name": "Alastair Darksmith",
        "inf_kills": 18,
        "soft_veh": 0,
        "armor_veh": 1,
        "air": 0,
        "deaths": 2,
        "score": 21
    },
    {
        "rank": 27,
        "name": "Locke Targarin",
        "inf_kills": 14,
        "soft_veh": 0,
        "armor_veh": 2,
        "air": 0,
        "deaths": 0,
        "score": 20
    },
    {
        "rank": 28,
        "name": "Jordan Drechsler",
        "inf_kills": 15,
        "soft_veh": 0,
        "armor_veh": 0,
        "air": 1,
        "deaths": 0,
        "score": 20
    },
    {
        "rank": 29,
        "name": "Konig Achen",
        "inf_kills": 23,
        "soft_veh": 0,
        "armor_veh": -1,
        "air": 0,
        "deaths": 5,
        "score": 20
    },
    {
        "rank": 30,
        "name": "Ven Erath",
        "inf_kills": 6,
        "soft_veh": 0,
        "armor_veh": 3,
        "air": 0,
        "deaths": 0,
        "score": 15
    },
    {
        "rank": 31,
        "name": "Cadmane Tureo",
        "inf_kills": 15,
        "soft_veh": 0,
        "armor_veh": 0,
        "air": 0,
        "deaths": 1,
        "score": 15
    },
    {
        "rank": 32,
        "name": "Farech Artiyald",
        "inf_kills": 10,
        "soft_veh": 0,
        "armor_veh": 1,
        "air": 0,
        "deaths": 0,
        "score": 13
    },
    {
        "rank": 33,
        "name": "Aray Armros",
        "inf_kills": 12,
        "soft_veh": 0,
        "armor_veh": 0,
        "air": 0,
        "deaths": 0,
        "score": 12
    },
    {
        "rank": 34,
        "name": "Terminus Undra",
        "inf_kills": 7,
        "soft_veh": 0,
        "armor_veh": 0,
        "air": 0,
        "deaths": 0,
        "score": 7
    },
    {
        "rank": 35,
        "name": "Lodus Koza",
        "inf_kills": 2,
        "soft_veh": 0,
        "armor_veh": 0,
        "air": 1,
        "deaths": 2,
        "score": 7
    },
    {
        "rank": 36,
        "name": "Voidens Arcnight",
        "inf_kills": 6,
        "soft_veh": 0,
        "armor_veh": -1,
        "air": 0,
        "deaths": 0,
        "score": 3
    },
    {
        "rank": 37,
        "name": "Wolf Tribune",
        "inf_kills": 2,
        "soft_veh": 0,
        "armor_veh": -2,
        "air": 1,
        "deaths": 0,
        "score": 1
    },
    {
        "rank": 38,
        "name": "Seraph Historia",
        "inf_kills": 0,
        "soft_veh": 0,
        "armor_veh": 0,
        "air": 0,
        "deaths": 0,
        "score": 0
    },
    {
        "rank": 39,
        "name": "Herius Occisor",
        "inf_kills": 0,
        "soft_veh": 0,
        "armor_veh": 0,
        "air": 0,
        "deaths": 0,
        "score": 0
    },
    {
        "rank": 40,
        "name": "Thalastia Asherion",
        "inf_kills": 0,
        "soft_veh": 0,
        "armor_veh": 0,
        "air": 0,
        "deaths": 0,
        "score": 0
    },
    {
        "rank": 41,
        "name": "Rukai Wolfhart",
        "inf_kills": 0,
        "soft_veh": 0,
        "armor_veh": 0,
        "air": 0,
        "deaths": 0,
        "score": 0
    }
]